mgmt/__init__.py
mgmt/logging.py
seartasw-0.1.0.dist-info/licenses/LICENSE
seartasw-0.1.0.dist-info/METADATA
seartasw-0.1.0.dist-info/WHEEL
seartasw-0.1.0.dist-info/top_level.txt
seartasw-0.1.0.dist-info/RECORD
