Metadata-Version: 2.4
Name: seartasw
Version: 0.1.0
Summary: Add your description here
Classifier: Operating System :: OS Independent
Requires-Python: >=3.11
License-File: LICENSE
Requires-Dist: azure-monitor-opentelemetry==1.6.10
Dynamic: license-file
